ods_models/__init__.py
ods_models/base.py
ods_models/brand.py
ods_models/canvas_globals.py
ods_models/font.py
ods_models/guides.py
ods_models/image.py
ods_models/input_parameters.py
ods_models/render_run.py
ods_models/template_input.py
ods_models/template_registry.py
ods_models_py-0.1.13.dist-info/METADATA
ods_models_py-0.1.13.dist-info/WHEEL
ods_models_py-0.1.13.dist-info/top_level.txt
ods_models_py-0.1.13.dist-info/RECORD
